deezer_oauth/__init__.py
deezer_oauth/__main__.py
deezer_oauth/client.py
deezer_oauth/constants.py
deezer_oauth/files.py
deezer_oauth/main.py
deezer_oauth/py.typed
deezer_oauth/server.py
deezer_oauth_cli-1.7.0.dist-info/licenses/LICENSE
deezer_oauth_cli-1.7.0.dist-info/METADATA
deezer_oauth_cli-1.7.0.dist-info/WHEEL
deezer_oauth_cli-1.7.0.dist-info/entry_points.txt
deezer_oauth_cli-1.7.0.dist-info/top_level.txt
deezer_oauth_cli-1.7.0.dist-info/RECORD
