Metadata-Version: 2.4
Name: deezer-oauth-cli
Version: 1.7.0
Summary: A small CLI to quickly obtain an API token for Deezer API.
Author-email: Bruno Alla <alla.brunoo@gmail.com>
License-Expression: MIT
Project-URL: Bug Tracker, https://github.com/browniebroke/deezer-oauth-cli/issues
Project-URL: Changelog, https://github.com/browniebroke/deezer-oauth-cli/blob/main/CHANGELOG.md
Project-URL: documentation, https://github.com/browniebroke/deezer-oauth-cli/blob/main/README.md
Project-URL: Mastodon, https://fosstodon.org/@browniebroke
Project-URL: repository, https://github.com/browniebroke/deezer-oauth-cli
Project-URL: Twitter, https://twitter.com/_BrunoAlla
Classifier: Development Status :: 2 - Pre-Alpha
Classifier: Intended Audience :: Developers
Classifier: Natural Language :: English
Classifier: Operating System :: OS Independent
Classifier: Programming Language :: Python :: 3 :: Only
Classifier: Programming Language :: Python :: 3.10
Classifier: Programming Language :: Python :: 3.11
Classifier: Programming Language :: Python :: 3.12
Classifier: Programming Language :: Python :: 3.13
Classifier: Programming Language :: Python :: 3.14
Classifier: Topic :: Software Development :: Libraries
Requires-Python: >=3.10
License-File: LICENSE
Requires-Dist: httpx>=0.27
Requires-Dist: rich>=10
Requires-Dist: typer>=0.12
Dynamic: license-file
